<?xml version="1.0" encoding="UTF-8"?>

<CHAT xmlns:xsi="http://www.w3.org/2001/XMLSchema-instance"
      xmlns="http://www.talkbank.org/ns/talkbank"
      xsi:schemaLocation="http://www.talkbank.org/ns/talkbank https://talkbank.org/software/talkbank.xsd"
      PID="11312/c-00029401-1"
      Version="2.7.1"
      Lang="fra"
      Corpus="MTLN"
      Date="1984-01-01">
  <Participants>
    <participant
      id="CHI"
    name="Christophe"
      role="Target_Child"
      language="fra"
      age="P2Y00M"
      sex="male"
      group="CTR"
      SES="MC"
      education="nursery"

    />
  </Participants>
  <comment type="Situation">replica task using FP play family house</comment>
  <u who="CHI" uID="u0">
    <w>dame<mor type="mor"><mw><pos><c>n</c></pos><stem>dame</stem><mk type="sfxf">f</mk></mw><menx>lady</menx></mor></w>
    <t type="p"><mor type="mor"><mt type="p"/></mor></t>

  </u>
  <u who="CHI" uID="u1">
    <w>caché<mor type="mor"><mw><pos><c>part</c></pos><stem>cacher</stem><mk type="sfx">PP</mk><mk type="sfxf">m</mk></mw></mor></w>
    <t type="p"><mor type="mor"><mt type="p"/></mor></t>

  </u>
  <u who="CHI" uID="u2">
    <w>encore<mor type="mor"><mw><pos><c>adv</c></pos><stem>encore</stem></mw></mor></w>
    <t type="p"><mor type="mor"><mt type="p"/></mor></t>

  </u>
  <u who="CHI" uID="u3">
    <w>elle<mor type="mor"><mw><pos><c>pro</c><s>subj</s></pos><stem>elle</stem></mw></mor></w>
    <w>est<mor type="mor"><mw><pos><c>v</c><s>aux</s></pos><stem>être</stem><mk type="sfxf">PRES</mk><mk type="sfxf">3s</mk></mw></mor></w>
    <w>dure<mor type="mor"><mw><pos><c>adj</c></pos><stem>dur</stem><mk type="sfxf">f</mk></mw></mor></w>
    <t type="p"><mor type="mor"><mt type="p"/></mor></t>

  </u>
  <u who="CHI" uID="u4">
    <w>bateau<mor type="mor"><mw><pos><c>n</c></pos><stem>bateau</stem><mk type="sfxf">m</mk></mw></mor></w>
    <t type="p"><mor type="mor"><mt type="p"/></mor></t>

  </u>
  <u who="CHI" uID="u5">
    <w>elle<mor type="mor"><mw><pos><c>pro</c><s>subj</s></pos><stem>elle</stem></mw></mor></w>
    <w>est<mor type="mor"><mw><pos><c>v</c><s>exist</s></pos><stem>être</stem><mk type="sfxf">PRES</mk><mk type="sfxf">3s</mk></mw></mor></w>
    <w>pas<mor type="mor"><mw><pos><c>adv</c><s>neg</s></pos><stem>pas</stem></mw></mor></w>
    <w>là<mor type="mor"><mw><pos><c>adv</c><s>place</s></pos><stem>là</stem></mw></mor></w>
    <t type="p"><mor type="mor"><mt type="p"/></mor></t>

  </u>
  <u who="CHI" uID="u6">
    <w>est<mor type="mor"><mw><pos><c>v</c><s>aux</s></pos><stem>être</stem><mk type="sfxf">PRES</mk><mk type="sfxf">3s</mk></mw></mor></w>
    <w>fermé<mor type="mor"><mw><pos><c>part</c></pos><stem>fermer</stem><mk type="sfx">PP</mk><mk type="sfxf">m</mk></mw></mor></w>
    <t type="p"><mor type="mor"><mt type="p"/></mor></t>

  </u>
  <u who="CHI" uID="u7">
    <w>est<mor type="mor"><mw><pos><c>v</c><s>aux</s></pos><stem>être</stem><mk type="sfxf">PRES</mk><mk type="sfxf">3s</mk></mw></mor></w>
    <w>là<mor type="mor"><mw><pos><c>adv</c><s>place</s></pos><stem>là</stem></mw></mor></w>
    <t type="p"><mor type="mor"><mt type="p"/></mor></t>

  </u>
  <u who="CHI" uID="u8">
    <w>fermé<mor type="mor"><mw><pos><c>adj</c></pos><stem>fermé</stem><mk type="sfxf">m</mk></mw></mor></w>
    <t type="p"><mor type="mor"><mt type="p"/></mor></t>

  </u>
  <u who="CHI" uID="u9">
    <w>voilà<mor type="mor"><mw><pos><c>adv</c><s>place</s></pos><stem>voilà</stem></mw></mor></w>
    <t type="p"><mor type="mor"><mt type="p"/></mor></t>

  </u>
  <u who="CHI" uID="u10">
    <w>comme-ça<mor type="mor"><mw><pos><c>adv</c></pos><stem>comme</stem><mk type="sfx">ça</mk></mw></mor></w>
    <t type="p"><mor type="mor"><mt type="p"/></mor></t>

  </u>
  <u who="CHI" uID="u11">
    <w>encore<mor type="mor"><mw><pos><c>adv</c></pos><stem>encore</stem></mw></mor></w>
    <t type="p"><mor type="mor"><mt type="p"/></mor></t>

  </u>
  <u who="CHI" uID="u12">
    <w>est<mor type="mor"><mw><pos><c>v</c><s>aux</s></pos><stem>être</stem><mk type="sfxf">PRES</mk><mk type="sfxf">3s</mk></mw></mor></w>
    <w>là<mor type="mor"><mw><pos><c>adv</c><s>place</s></pos><stem>là</stem></mw></mor></w>
    <t type="p"><mor type="mor"><mt type="p"/></mor></t>

  </u>
  <u who="CHI" uID="u13">
    <w>fermé<mor type="mor"><mw><pos><c>adj</c></pos><stem>fermé</stem><mk type="sfxf">m</mk></mw></mor></w>
    <t type="p"><mor type="mor"><mt type="p"/></mor></t>

  </u>
  <u who="CHI" uID="u14">
    <w>tombé<mor type="mor"><mw><pos><c>part</c></pos><stem>tomber</stem><mk type="sfx">PP</mk><mk type="sfxf">m</mk></mw></mor></w>
    <t type="p"><mor type="mor"><mt type="p"/></mor></t>

  </u>
  <u who="CHI" uID="u15">
    <w>est<mor type="mor"><mw><pos><c>v</c><s>aux</s></pos><stem>être</stem><mk type="sfxf">PRES</mk><mk type="sfxf">3s</mk></mw></mor></w>
    <w>mignon<mor type="mor"><mw><pos><c>n</c></pos><stem>mignon</stem><mk type="sfxf">m</mk></mw></mor></w>
    <t type="p"><mor type="mor"><mt type="p"/></mor></t>

  </u>
  <u who="CHI" uID="u16">
    <w>c'est<mor type="mor"><mw><pos><c>v</c><s>aux</s></pos><stem>être</stem><mk type="sfxf">PRES</mk><mk type="sfxf">3s</mk></mw><mor-pre><mw><pos><c>pro</c><s>dem</s></pos><stem>ce</stem></mw></mor-pre></mor></w>
    <w>papa<mor type="mor"><mw><pos><c>n</c></pos><stem>papa</stem><mk type="sfxf">m</mk></mw></mor></w>
    <w>conduit<mor type="mor"><mw><pos><c>n</c></pos><stem>conduit</stem><mk type="sfxf">m</mk></mw></mor></w>
    <t type="p"><mor type="mor"><mt type="p"/></mor></t>

  </u>
  <u who="CHI" uID="u17">
    <w>est<mor type="mor"><mw><pos><c>v</c><s>aux</s></pos><stem>être</stem><mk type="sfxf">PRES</mk><mk type="sfxf">3s</mk></mw></mor></w>
    <w>à<mor type="mor"><mw><pos><c>prep</c></pos><stem>à</stem></mw></mor></w>
    <w>papa<mor type="mor"><mw><pos><c>n</c></pos><stem>papa</stem><mk type="sfxf">m</mk></mw></mor></w>
    <t type="p"><mor type="mor"><mt type="p"/></mor></t>

  </u>
  <u who="CHI" uID="u18">
    <w>autre<mor type="mor"><mw><pos><c>pro</c></pos><stem>autre</stem><mk type="sfxf">sg</mk></mw></mor></w>
    <w>côté<mor type="mor"><mw><pos><c>n</c></pos><stem>côté</stem><mk type="sfxf">m</mk></mw></mor></w>
    <t type="p"><mor type="mor"><mt type="p"/></mor></t>

  </u>
  <u who="CHI" uID="u19">
    <w>voilà<mor type="mor"><mw><pos><c>adv</c><s>place</s></pos><stem>voilà</stem></mw></mor></w>
    <t type="p"><mor type="mor"><mt type="p"/></mor></t>

  </u>
  <u who="CHI" uID="u20">
    <w>au_revoir<mor type="mor"><mw><pos><c>co</c></pos><stem>au_revoir</stem></mw></mor></w>
    <t type="p"><mor type="mor"><mt type="p"/></mor></t>

  </u>
  <u who="CHI" uID="u21">
    <w>boum<mor type="mor"><mw><pos><c>co</c></pos><stem>boum</stem></mw></mor></w>
    <t type="p"><mor type="mor"><mt type="p"/></mor></t>

  </u>
  <u who="CHI" uID="u22">
    <w>voilà<mor type="mor"><mw><pos><c>adv</c><s>place</s></pos><stem>voilà</stem></mw></mor></w>
    <t type="p"><mor type="mor"><mt type="p"/></mor></t>

  </u>
  <u who="CHI" uID="u23">
    <w>est<mor type="mor"><mw><pos><c>v</c><s>aux</s></pos><stem>être</stem><mk type="sfxf">PRES</mk><mk type="sfxf">3s</mk></mw></mor></w>
    <w>fermé<mor type="mor"><mw><pos><c>part</c></pos><stem>fermer</stem><mk type="sfx">PP</mk><mk type="sfxf">m</mk></mw></mor></w>
    <t type="p"><mor type="mor"><mt type="p"/></mor></t>

  </u>
  <u who="CHI" uID="u24">
    <w>est<mor type="mor"><mw><pos><c>v</c><s>aux</s></pos><stem>être</stem><mk type="sfxf">PRES</mk><mk type="sfxf">3s</mk></mw></mor></w>
    <w>pu<mor type="mor"><mw><pos><c>part</c></pos><stem>pouvoir</stem><mk type="sfxf">PP</mk><mk type="sfxf">m</mk><mk type="sfxf">sg</mk></mw></mor></w>
    <w>là<mor type="mor"><mw><pos><c>adv</c><s>place</s></pos><stem>là</stem></mw></mor></w>
    <t type="p"><mor type="mor"><mt type="p"/></mor></t>

  </u>
  <u who="CHI" uID="u25">
    <w>fermé<mor type="mor"><mw><pos><c>adj</c></pos><stem>fermé</stem><mk type="sfxf">m</mk></mw></mor></w>
    <w>la<mor type="mor"><mw><pos><c>det</c><s>art</s></pos><stem>la</stem><mk type="sfxf">f</mk><mk type="sfxf">sg</mk></mw></mor></w>
    <w>porte<mor type="mor"><mw><pos><c>n</c></pos><stem>porte</stem><mk type="sfxf">f</mk></mw><menx>door</menx></mor></w>
    <t type="p"><mor type="mor"><mt type="p"/></mor></t>

  </u>
  <u who="CHI" uID="u26">
    <w>fermé<mor type="mor"><mw><pos><c>adj</c></pos><stem>fermé</stem><mk type="sfxf">m</mk></mw></mor></w>
    <t type="p"><mor type="mor"><mt type="p"/></mor></t>

  </u>
  <u who="CHI" uID="u27">
    <w>oh<mor type="mor"><mw><pos><c>co</c></pos><stem>oh</stem></mw></mor></w>
    <w>regarde<mor type="mor"><mw><pos><c>v</c></pos><stem>regarder</stem><mk type="sfx">IMP</mk><mk type="sfxf">2s</mk></mw></mor></w>
    <t type="p"><mor type="mor"><mt type="p"/></mor></t>

  </u>
  <u who="CHI" uID="u28">
    <w>bébé<mor type="mor"><mw><pos><c>n</c></pos><stem>bébé</stem><mk type="sfxf">m</mk></mw></mor></w>
    <t type="p"><mor type="mor"><mt type="p"/></mor></t>

  </u>
  <u who="CHI" uID="u29">
    <w>y<mor type="mor"><mw><pos><c>pro</c><s>y</s></pos><stem>y</stem></mw></mor></w>
    <w>a<mor type="mor"><mw><pos><c>v</c><s>aux</s></pos><stem>avoir</stem><mk type="sfxf">PRES</mk><mk type="sfxf">3s</mk></mw></mor></w>
    <w>pas<mor type="mor"><mw><pos><c>adv</c><s>neg</s></pos><stem>pas</stem></mw></mor></w>
    <w>couvercle<mor type="mor"><mw><pos><c>n</c></pos><stem>couvercle</stem><mk type="sfxf">m</mk></mw></mor></w>
    <t type="p"><mor type="mor"><mt type="p"/></mor></t>

  </u>
  <u who="CHI" uID="u30">
    <w>pour<mor type="mor"><mw><pos><c>prep</c></pos><stem>pour</stem></mw></mor></w>
    <w>dodo<mor type="mor"><mw><pos><c>n</c></pos><stem>dodo</stem><mk type="sfxf">m</mk></mw><menx>sleep</menx></mor></w>
    <t type="p"><mor type="mor"><mt type="p"/></mor></t>

  </u>
  <u who="CHI" uID="u31">
    <w>beau<mor type="mor"><mw><pos><c>adj</c></pos><stem>beau</stem><mk type="sfxf">m</mk><mk type="sfxf">sg</mk></mw><menx>pretty</menx></mor></w>
    <w>dodo<mor type="mor"><mw><pos><c>n</c></pos><stem>dodo</stem><mk type="sfxf">m</mk></mw><menx>sleep</menx></mor></w>
    <t type="p"><mor type="mor"><mt type="p"/></mor></t>

  </u>
  <u who="CHI" uID="u32">
    <w>y<mor type="mor"><mw><pos><c>pro</c><s>y</s></pos><stem>y</stem></mw></mor></w>
    <w>a<mor type="mor"><mw><pos><c>v</c><s>aux</s></pos><stem>avoir</stem><mk type="sfxf">PRES</mk><mk type="sfxf">3s</mk></mw></mor></w>
    <w>pu<mor type="mor"><mw><pos><c>part</c></pos><stem>pouvoir</stem><mk type="sfxf">PP</mk><mk type="sfxf">m</mk><mk type="sfxf">sg</mk></mw></mor></w>
    <w>mon<mor type="mor"><mw><pos><c>det</c><s>poss</s></pos><stem>mon</stem><mk type="sfxf">m</mk><mk type="sfxf">sg</mk></mw></mor></w>
    <w>dodo<mor type="mor"><mw><pos><c>n</c></pos><stem>dodo</stem><mk type="sfxf">m</mk></mw><menx>sleep</menx></mor></w>
    <t type="p"><mor type="mor"><mt type="p"/></mor></t>

  </u>
  <u who="CHI" uID="u33">
    <w>voilà<mor type="mor"><mw><pos><c>adv</c><s>place</s></pos><stem>voilà</stem></mw></mor></w>
    <t type="p"><mor type="mor"><mt type="p"/></mor></t>

  </u>
  <u who="CHI" uID="u34">
    <w>tombé<mor type="mor"><mw><pos><c>part</c></pos><stem>tomber</stem><mk type="sfx">PP</mk><mk type="sfxf">m</mk></mw></mor></w>
    <t type="p"><mor type="mor"><mt type="p"/></mor></t>

  </u>
  <u who="CHI" uID="u35">
    <w>y<mor type="mor"><mw><pos><c>pro</c><s>y</s></pos><stem>y</stem></mw></mor></w>
    <w>a<mor type="mor"><mw><pos><c>v</c><s>aux</s></pos><stem>avoir</stem><mk type="sfxf">PRES</mk><mk type="sfxf">3s</mk></mw></mor></w>
    <w>pas<mor type="mor"><mw><pos><c>adv</c><s>neg</s></pos><stem>pas</stem></mw></mor></w>
    <t type="p"><mor type="mor"><mt type="p"/></mor></t>

  </u>
  <u who="CHI" uID="u36">
    <w>un<mor type="mor"><mw><pos><c>det</c><s>art</s></pos><stem>un</stem><mk type="sfxf">m</mk><mk type="sfxf">sg</mk></mw></mor></w>
    <w>bisou<mor type="mor"><mw><pos><c>n</c></pos><stem>bisou</stem><mk type="sfxf">m</mk></mw></mor></w>
    <t type="p"><mor type="mor"><mt type="p"/></mor></t>

  </u>
  <u who="CHI" uID="u37">
    <w>a<mor type="mor"><mw><pos><c>v</c><s>aux</s></pos><stem>avoir</stem><mk type="sfxf">PRES</mk><mk type="sfxf">3s</mk></mw></mor></w>
    <w>pu<mor type="mor"><mw><pos><c>part</c></pos><stem>pouvoir</stem><mk type="sfxf">PP</mk><mk type="sfxf">m</mk><mk type="sfxf">sg</mk></mw></mor></w>
    <w>wouwou<mor type="mor"><mw><pos><c>co</c></pos><stem>wouwou</stem></mw></mor></w>
    <t type="p"><mor type="mor"><mt type="p"/></mor></t>

  </u>
  <u who="CHI" uID="u38">
    <w>attends<mor type="mor"><mw><pos><c>v</c></pos><stem>attendre</stem><mk type="sfx">IMP</mk><mk type="sfxf">2s</mk></mw></mor></w>
    <t type="p"><mor type="mor"><mt type="p"/></mor></t>

  </u>
  <u who="CHI" uID="u39">
    <w>tout<mor type="mor"><mw><pos><c>adv</c></pos><stem>tout</stem></mw></mor></w>
    <w>tombé<mor type="mor"><mw><pos><c>part</c></pos><stem>tomber</stem><mk type="sfx">PP</mk><mk type="sfxf">m</mk></mw></mor></w>
    <t type="p"><mor type="mor"><mt type="p"/></mor></t>

  </u>
  <u who="CHI" uID="u40">
    <w>caché<mor type="mor"><mw><pos><c>part</c></pos><stem>cacher</stem><mk type="sfx">PP</mk><mk type="sfxf">m</mk></mw></mor></w>
    <t type="p"><mor type="mor"><mt type="p"/></mor></t>

  </u>
  <u who="CHI" uID="u41">
    <w>est<mor type="mor"><mw><pos><c>v</c><s>aux</s></pos><stem>être</stem><mk type="sfxf">PRES</mk><mk type="sfxf">3s</mk></mw></mor></w>
    <w>dure<mor type="mor"><mw><pos><c>adj</c></pos><stem>dur</stem><mk type="sfxf">f</mk></mw></mor></w>
    <w>la<mor type="mor"><mw><pos><c>det</c><s>art</s></pos><stem>la</stem><mk type="sfxf">f</mk><mk type="sfxf">sg</mk></mw></mor></w>
    <w>porte<mor type="mor"><mw><pos><c>n</c></pos><stem>porte</stem><mk type="sfxf">f</mk></mw><menx>door</menx></mor></w>
    <t type="p"><mor type="mor"><mt type="p"/></mor></t>

  </u>
  <u who="CHI" uID="u42">
    <w>elle<mor type="mor"><mw><pos><c>pro</c><s>subj</s></pos><stem>elle</stem></mw></mor></w>
    <w>est<mor type="mor"><mw><pos><c>v</c><s>aux</s></pos><stem>être</stem><mk type="sfxf">PRES</mk><mk type="sfxf">3s</mk></mw></mor></w>
    <w>fermée<mor type="mor"><mw><pos><c>part</c></pos><stem>fermer</stem><mk type="sfx">PP</mk><mk type="sfxf">f</mk></mw></mor></w>
    <w>la<mor type="mor"><mw><pos><c>det</c><s>art</s></pos><stem>la</stem><mk type="sfxf">f</mk><mk type="sfxf">sg</mk></mw></mor></w>
    <w>porte<mor type="mor"><mw><pos><c>n</c></pos><stem>porte</stem><mk type="sfxf">f</mk></mw><menx>door</menx></mor></w>
    <t type="p"><mor type="mor"><mt type="p"/></mor></t>

  </u>
  <u who="CHI" uID="u43">
    <w>ah<mor type="mor"><mw><pos><c>co</c></pos><stem>ah</stem></mw></mor></w>
    <w>voilà<mor type="mor"><mw><pos><c>adv</c><s>place</s></pos><stem>voilà</stem></mw></mor></w>
    <t type="p"><mor type="mor"><mt type="p"/></mor></t>

  </u>
  <u who="CHI" uID="u44">
    <w>tombé<mor type="mor"><mw><pos><c>part</c></pos><stem>tomber</stem><mk type="sfx">PP</mk><mk type="sfxf">m</mk></mw></mor></w>
    <t type="p"><mor type="mor"><mt type="p"/></mor></t>

  </u>
  <u who="CHI" uID="u45">
    <w>c'est<mor type="mor"><mw><pos><c>v</c><s>aux</s></pos><stem>être</stem><mk type="sfxf">PRES</mk><mk type="sfxf">3s</mk></mw><mor-pre><mw><pos><c>pro</c><s>dem</s></pos><stem>ce</stem></mw></mor-pre></mor></w>
    <w>fermé<mor type="mor"><mw><pos><c>part</c></pos><stem>fermer</stem><mk type="sfx">PP</mk><mk type="sfxf">m</mk></mw></mor></w>
    <t type="p"><mor type="mor"><mt type="p"/></mor></t>

  </u>
  <u who="CHI" uID="u46">
    <w>tombé<mor type="mor"><mw><pos><c>part</c></pos><stem>tomber</stem><mk type="sfx">PP</mk><mk type="sfxf">m</mk></mw></mor></w>
    <t type="p"><mor type="mor"><mt type="p"/></mor></t>

  </u>
  <u who="CHI" uID="u47">
    <w>est<mor type="mor"><mw><pos><c>v</c><s>aux</s></pos><stem>être</stem><mk type="sfxf">PRES</mk><mk type="sfxf">3s</mk></mw></mor></w>
    <w>mignonne<mor type="mor"><mw><pos><c>n</c></pos><stem>mignonne</stem><mk type="sfxf">f</mk></mw></mor></w>
    <t type="p"><mor type="mor"><mt type="p"/></mor></t>

  </u>
  <u who="CHI" uID="u48">
    <w>télé<mor type="mor"><mw><pos><c>n</c></pos><stem>télé</stem><mk type="sfxf">f</mk></mw><menx>television</menx></mor></w>
    <t type="p"><mor type="mor"><mt type="p"/></mor></t>

  </u>
  <u who="CHI" uID="u49">
    <w>ah<mor type="mor"><mw><pos><c>co</c></pos><stem>ah</stem></mw></mor></w>
    <w>l'a<mor type="mor"><mw><pos><c>v</c><s>aux</s></pos><stem>avoir</stem><mk type="sfxf">PRES</mk><mk type="sfxf">3s</mk></mw><mor-pre><mw><pos><c>pro</c><s>subj</s></pos><stem>il</stem></mw></mor-pre></mor></w>
    <w>pu<mor type="mor"><mw><pos><c>part</c></pos><stem>pouvoir</stem><mk type="sfxf">PP</mk><mk type="sfxf">m</mk><mk type="sfxf">sg</mk></mw></mor></w>
    <t type="p"><mor type="mor"><mt type="p"/></mor></t>

  </u>
  <u who="CHI" uID="u50">
    <w>est<mor type="mor"><mw><pos><c>v</c><s>aux</s></pos><stem>être</stem><mk type="sfxf">PRES</mk><mk type="sfxf">3s</mk></mw></mor></w>
    <w>tombé<mor type="mor"><mw><pos><c>part</c></pos><stem>tomber</stem><mk type="sfx">PP</mk><mk type="sfxf">m</mk></mw></mor></w>
    <t type="p"><mor type="mor"><mt type="p"/></mor></t>

  </u>
  <u who="CHI" uID="u51">
    <w>est<mor type="mor"><mw><pos><c>v</c><s>aux</s></pos><stem>être</stem><mk type="sfxf">PRES</mk><mk type="sfxf">3s</mk></mw></mor></w>
    <w>tombé<mor type="mor"><mw><pos><c>part</c></pos><stem>tomber</stem><mk type="sfx">PP</mk><mk type="sfxf">m</mk></mw></mor></w>
    <t type="p"><mor type="mor"><mt type="p"/></mor></t>

  </u>
  <u who="CHI" uID="u52">
    <w>tombé<mor type="mor"><mw><pos><c>part</c></pos><stem>tomber</stem><mk type="sfx">PP</mk><mk type="sfxf">m</mk></mw></mor></w>
    <t type="p"><mor type="mor"><mt type="p"/></mor></t>

  </u>
  <u who="CHI" uID="u53">
    <w>est<mor type="mor"><mw><pos><c>v</c><s>aux</s></pos><stem>être</stem><mk type="sfxf">PRES</mk><mk type="sfxf">3s</mk></mw></mor></w>
    <w>tombé<mor type="mor"><mw><pos><c>part</c></pos><stem>tomber</stem><mk type="sfx">PP</mk><mk type="sfxf">m</mk></mw></mor></w>
    <t type="p"><mor type="mor"><mt type="p"/></mor></t>

  </u>
  <u who="CHI" uID="u54">
    <w>est<mor type="mor"><mw><pos><c>v</c><s>aux</s></pos><stem>être</stem><mk type="sfxf">PRES</mk><mk type="sfxf">3s</mk></mw></mor></w>
    <w>tombée<mor type="mor"><mw><pos><c>part</c></pos><stem>tomber</stem><mk type="sfx">PP</mk><mk type="sfxf">f</mk></mw></mor></w>
    <t type="p"><mor type="mor"><mt type="p"/></mor></t>

  </u>
  <u who="CHI" uID="u55">
    <w>coucou<mor type="mor"><mw><pos><c>co</c></pos><stem>coucou</stem></mw><menx>peekaboo</menx></mor></w>
    <t type="p"><mor type="mor"><mt type="p"/></mor></t>

  </u>
  <u who="CHI" uID="u56">
    <w>dodo<mor type="mor"><mw><pos><c>co</c></pos><stem>dodo</stem></mw></mor></w>
    <t type="p"><mor type="mor"><mt type="p"/></mor></t>

  </u>
  <u who="CHI" uID="u57">
    <w>encore<mor type="mor"><mw><pos><c>adv</c></pos><stem>encore</stem></mw></mor></w>
    <t type="p"><mor type="mor"><mt type="p"/></mor></t>

  </u>
  <u who="CHI" uID="u58">
    <w>tombé<mor type="mor"><mw><pos><c>part</c></pos><stem>tomber</stem><mk type="sfx">PP</mk><mk type="sfxf">m</mk></mw></mor></w>
    <t type="p"><mor type="mor"><mt type="p"/></mor></t>

  </u>
  <u who="CHI" uID="u59">
    <w>ramasse<mor type="mor"><mw><pos><c>v</c></pos><stem>ramasser</stem><mk type="sfx">IMP</mk><mk type="sfxf">2s</mk></mw></mor></w>
    <t type="e"><mor type="mor"><mt type="e"/></mor></t>

  </u>
  <u who="CHI" uID="u60">
    <w>bébé<mor type="mor"><mw><pos><c>n</c></pos><stem>bébé</stem><mk type="sfxf">m</mk></mw></mor></w>
    <t type="p"><mor type="mor"><mt type="p"/></mor></t>

  </u>
  <u who="CHI" uID="u61">
    <w>pas<mor type="mor"><mw><pos><c>adv</c><s>neg</s></pos><stem>pas</stem></mw></mor></w>
    <w>allo<mor type="mor"><mw><pos><c>co</c></pos><stem>allo</stem></mw></mor></w>
    <t type="p"><mor type="mor"><mt type="p"/></mor></t>

  </u>
  <u who="CHI" uID="u62">
    <w>télé<mor type="mor"><mw><pos><c>n</c></pos><stem>télé</stem><mk type="sfxf">f</mk></mw><menx>television</menx></mor></w>
    <t type="p"><mor type="mor"><mt type="p"/></mor></t>

  </u>
  <u who="CHI" uID="u63">
    <w>est<mor type="mor"><mw><pos><c>v</c><s>aux</s></pos><stem>être</stem><mk type="sfxf">PRES</mk><mk type="sfxf">3s</mk></mw></mor></w>
    <w>mignonne<mor type="mor"><mw><pos><c>n</c></pos><stem>mignonne</stem><mk type="sfxf">f</mk></mw></mor></w>
    <t type="p"><mor type="mor"><mt type="p"/></mor></t>

  </u>
  <u who="CHI" uID="u64">
    <w>est<mor type="mor"><mw><pos><c>v</c><s>aux</s></pos><stem>être</stem><mk type="sfxf">PRES</mk><mk type="sfxf">3s</mk></mw></mor></w>
    <w>tombé<mor type="mor"><mw><pos><c>part</c></pos><stem>tomber</stem><mk type="sfx">PP</mk><mk type="sfxf">m</mk></mw></mor></w>
    <t type="p"><mor type="mor"><mt type="p"/></mor></t>

  </u>
  <u who="CHI" uID="u65">
    <w>tombé<mor type="mor"><mw><pos><c>part</c></pos><stem>tomber</stem><mk type="sfx">PP</mk><mk type="sfxf">m</mk></mw></mor></w>
    <t type="p"><mor type="mor"><mt type="p"/></mor></t>

  </u>
</CHAT>