<?xml version="1.0" encoding="UTF-8"?>

<CHAT xmlns:xsi="http://www.w3.org/2001/XMLSchema-instance"
      xmlns="http://www.talkbank.org/ns/talkbank"
      xsi:schemaLocation="http://www.talkbank.org/ns/talkbank https://talkbank.org/software/talkbank.xsd"
      PID="11312/c-00029526-1"
      Version="2.7.1"
      Lang="fra"
      Corpus="MTLN"
      Date="1984-01-01">
  <Participants>
    <participant
      id="CHI"
    name="Marion"
      role="Target_Child"
      language="fra"
      age="P2Y09M"
      sex="female"
      group="CTR"
      SES="MC"
      education="Home"

    />
  </Participants>
  <comment type="Situation">replica task using FP play family house</comment>
  <u who="CHI" uID="u0">
    <w>celle-là<mor type="mor"><mw><pos><c>pro</c><s>dem</s></pos><stem>celle</stem><mk type="sfx">là</mk></mw></mor></w>
    <t type="p"><mor type="mor"><mt type="p"/></mor></t>

  </u>
  <u who="CHI" uID="u1">
    <w>c'est<mor type="mor"><mw><pos><c>v</c><s>aux</s></pos><stem>être</stem><mk type="sfxf">PRES</mk><mk type="sfxf">3s</mk></mw><mor-pre><mw><pos><c>pro</c><s>dem</s></pos><stem>ce</stem></mw></mor-pre></mor></w>
    <w>un<mor type="mor"><mw><pos><c>det</c><s>art</s></pos><stem>un</stem><mk type="sfxf">m</mk><mk type="sfxf">sg</mk></mw></mor></w>
    <w>cheval<mor type="mor"><mw><pos><c>n</c></pos><stem>cheval</stem><mk type="sfxf">m</mk><mk type="sfxf">sg</mk></mw></mor></w>
    <t type="p"><mor type="mor"><mt type="p"/></mor></t>

  </u>
  <u who="CHI" uID="u2">
    <w>bêbêbêbê<mor type="mor"><mw><pos><c>co</c></pos><stem>bêbêbêbê</stem></mw></mor></w>
    <t type="p"><mor type="mor"><mt type="p"/></mor></t>

  </u>
  <u who="CHI" uID="u3">
    <w>oh<mor type="mor"><mw><pos><c>co</c></pos><stem>oh</stem></mw></mor></w>
    <t type="e"><mor type="mor"><mt type="e"/></mor></t>

  </u>
  <u who="CHI" uID="u4">
    <w>oh<mor type="mor"><mw><pos><c>co</c></pos><stem>oh</stem></mw></mor></w>
    <w>il<mor type="mor"><mw><pos><c>pro</c><s>subj</s></pos><stem>il</stem></mw></mor></w>
    <w>est<mor type="mor"><mw><pos><c>v</c><s>aux</s></pos><stem>être</stem><mk type="sfxf">PRES</mk><mk type="sfxf">3s</mk></mw></mor></w>
    <w>tombé<mor type="mor"><mw><pos><c>part</c></pos><stem>tomber</stem><mk type="sfx">PP</mk><mk type="sfxf">m</mk></mw></mor></w>
    <t type="p"><mor type="mor"><mt type="p"/></mor></t>

  </u>
  <u who="CHI" uID="u5">
    <w>oui<mor type="mor"><mw><pos><c>co</c></pos><stem>oui</stem></mw><menx>yes</menx></mor></w>
    <t type="p"><mor type="mor"><mt type="p"/></mor></t>

  </u>
  <u who="CHI" uID="u6">
    <w>sur<mor type="mor"><mw><pos><c>prep</c></pos><stem>sur</stem></mw></mor></w>
    <w>la<mor type="mor"><mw><pos><c>det</c><s>art</s></pos><stem>la</stem><mk type="sfxf">f</mk><mk type="sfxf">sg</mk></mw></mor></w>
    <w>route<mor type="mor"><mw><pos><c>n</c></pos><stem>route</stem><mk type="sfxf">f</mk></mw></mor></w>
    <t type="p"><mor type="mor"><mt type="p"/></mor></t>

  </u>
  <u who="CHI" uID="u7">
    <w>c'est<mor type="mor"><mw><pos><c>v</c><s>aux</s></pos><stem>être</stem><mk type="sfxf">PRES</mk><mk type="sfxf">3s</mk></mw><mor-pre><mw><pos><c>pro</c><s>dem</s></pos><stem>ce</stem></mw></mor-pre></mor></w>
    <w>un<mor type="mor"><mw><pos><c>det</c><s>art</s></pos><stem>un</stem><mk type="sfxf">m</mk><mk type="sfxf">sg</mk></mw></mor></w>
    <w>lit<mor type="mor"><mw><pos><c>n</c></pos><stem>lit</stem><mk type="sfxf">m</mk></mw></mor></w>
    <w>ça<mor type="mor"><mw><pos><c>pro</c><s>dem</s></pos><stem>ça</stem></mw></mor></w>
    <t type="p"><mor type="mor"><mt type="p"/></mor></t>

  </u>
  <u who="CHI" uID="u8">
    <w>fait<mor type="mor"><mw><pos><c>part</c></pos><stem>faire</stem><mk type="sfx">PP</mk><mk type="sfxf">m</mk></mw></mor></w>
    <w>dodo<mor type="mor"><mw><pos><c>n</c></pos><stem>dodo</stem><mk type="sfxf">m</mk></mw><menx>sleep</menx></mor></w>
    <t type="p"><mor type="mor"><mt type="p"/></mor></t>

  </u>
  <u who="CHI" uID="u9">
    <w>oh<mor type="mor"><mw><pos><c>co</c></pos><stem>oh</stem></mw></mor></w>
    <t type="e"><mor type="mor"><mt type="e"/></mor></t>

  </u>
  <u who="CHI" uID="u10">
    <w>oui<mor type="mor"><mw><pos><c>co</c></pos><stem>oui</stem></mw><menx>yes</menx></mor></w>
    <t type="p"><mor type="mor"><mt type="p"/></mor></t>

  </u>
  <u who="CHI" uID="u11">
    <w>oh<mor type="mor"><mw><pos><c>co</c></pos><stem>oh</stem></mw></mor></w>
    <w>y<mor type="mor"><mw><pos><c>pro</c><s>y</s></pos><stem>y</stem></mw></mor></w>
    <w>a<mor type="mor"><mw><pos><c>v</c><s>aux</s></pos><stem>avoir</stem><mk type="sfxf">PRES</mk><mk type="sfxf">3s</mk></mw></mor></w>
    <w>pas<mor type="mor"><mw><pos><c>adv</c><s>neg</s></pos><stem>pas</stem></mw></mor></w>
    <w>de<mor type="mor"><mw><pos><c>prep</c></pos><stem>de</stem></mw></mor></w>
    <w>place<mor type="mor"><mw><pos><c>n</c></pos><stem>place</stem><mk type="sfxf">f</mk></mw></mor></w>
    <t type="e"><mor type="mor"><mt type="e"/></mor></t>

  </u>
  <u who="CHI" uID="u12">
    <w>il<mor type="mor"><mw><pos><c>pro</c><s>subj</s></pos><stem>il</stem></mw></mor></w>
    <w>a<mor type="mor"><mw><pos><c>v</c><s>aux</s></pos><stem>avoir</stem><mk type="sfxf">PRES</mk><mk type="sfxf">3s</mk></mw></mor></w>
    <w>dormi<mor type="mor"><mw><pos><c>part</c></pos><stem>dormir</stem><mk type="sfx">PP</mk><mk type="sfxf">m</mk></mw></mor></w>
    <t type="p"><mor type="mor"><mt type="p"/></mor></t>

  </u>
  <u who="CHI" uID="u13">
    <w>vroum<mor type="mor"><mw><pos><c>co</c></pos><stem>vroum</stem></mw><menx>car</menx></mor></w>
    <t type="e"><mor type="mor"><mt type="e"/></mor></t>

  </u>
  <u who="CHI" uID="u14">
    <w>là<mor type="mor"><mw><pos><c>adv</c><s>place</s></pos><stem>là</stem></mw></mor></w>
    <w>y<mor type="mor"><mw><pos><c>pro</c><s>y</s></pos><stem>y</stem></mw></mor></w>
    <w>a<mor type="mor"><mw><pos><c>v</c><s>aux</s></pos><stem>avoir</stem><mk type="sfxf">PRES</mk><mk type="sfxf">3s</mk></mw></mor></w>
    <w>pas<mor type="mor"><mw><pos><c>adv</c><s>neg</s></pos><stem>pas</stem></mw></mor></w>
    <w>la<mor type="mor"><mw><pos><c>det</c><s>art</s></pos><stem>la</stem><mk type="sfxf">f</mk><mk type="sfxf">sg</mk></mw></mor></w>
    <w>place<mor type="mor"><mw><pos><c>n</c></pos><stem>place</stem><mk type="sfxf">f</mk></mw></mor></w>
    <t type="p"><mor type="mor"><mt type="p"/></mor></t>

  </u>
  <u who="CHI" uID="u15">
    <w>il<mor type="mor"><mw><pos><c>pro</c><s>subj</s></pos><stem>il</stem></mw></mor></w>
    <w>a<mor type="mor"><mw><pos><c>v</c><s>aux</s></pos><stem>avoir</stem><mk type="sfxf">PRES</mk><mk type="sfxf">3s</mk></mw></mor></w>
    <w>dormi<mor type="mor"><mw><pos><c>part</c></pos><stem>dormir</stem><mk type="sfx">PP</mk><mk type="sfxf">m</mk></mw></mor></w>
    <t type="p"><mor type="mor"><mt type="p"/></mor></t>

  </u>
  <u who="CHI" uID="u16">
    <w>vroum<mor type="mor"><mw><pos><c>co</c></pos><stem>vroum</stem></mw><menx>car</menx></mor></w>
    <t type="e"><mor type="mor"><mt type="e"/></mor></t>

  </u>
  <u who="CHI" uID="u17">
    <w>là<mor type="mor"><mw><pos><c>adv</c><s>place</s></pos><stem>là</stem></mw></mor></w>
    <w>y<mor type="mor"><mw><pos><c>pro</c><s>y</s></pos><stem>y</stem></mw></mor></w>
    <w>a<mor type="mor"><mw><pos><c>v</c><s>aux</s></pos><stem>avoir</stem><mk type="sfxf">PRES</mk><mk type="sfxf">3s</mk></mw></mor></w>
    <w>de<mor type="mor"><mw><pos><c>prep</c></pos><stem>de</stem></mw></mor></w>
    <w>la<mor type="mor"><mw><pos><c>det</c><s>art</s></pos><stem>la</stem><mk type="sfxf">f</mk><mk type="sfxf">sg</mk></mw></mor></w>
    <w>place<mor type="mor"><mw><pos><c>n</c></pos><stem>place</stem><mk type="sfxf">f</mk></mw></mor></w>
    <t type="e"><mor type="mor"><mt type="e"/></mor></t>

  </u>
  <u who="CHI" uID="u18">
    <w>y<mor type="mor"><mw><pos><c>pro</c><s>y</s></pos><stem>y</stem></mw></mor></w>
    <w>a<mor type="mor"><mw><pos><c>v</c><s>aux</s></pos><stem>avoir</stem><mk type="sfxf">PRES</mk><mk type="sfxf">3s</mk></mw></mor></w>
    <w>de<mor type="mor"><mw><pos><c>prep</c></pos><stem>de</stem></mw></mor></w>
    <w>la<mor type="mor"><mw><pos><c>det</c><s>art</s></pos><stem>la</stem><mk type="sfxf">f</mk><mk type="sfxf">sg</mk></mw></mor></w>
    <w>place<mor type="mor"><mw><pos><c>n</c></pos><stem>place</stem><mk type="sfxf">f</mk></mw></mor></w>
    <t type="p"><mor type="mor"><mt type="p"/></mor></t>

  </u>
  <u who="CHI" uID="u19">
    <w>regarde<mor type="mor"><mw><pos><c>v</c></pos><stem>regarder</stem><mk type="sfx">IMP</mk><mk type="sfxf">2s</mk></mw></mor></w>
    <w>y<mor type="mor"><mw><pos><c>pro</c><s>y</s></pos><stem>y</stem></mw></mor></w>
    <w>a<mor type="mor"><mw><pos><c>v</c><s>aux</s></pos><stem>avoir</stem><mk type="sfxf">PRES</mk><mk type="sfxf">3s</mk></mw></mor></w>
    <w>de<mor type="mor"><mw><pos><c>prep</c></pos><stem>de</stem></mw></mor></w>
    <w>la<mor type="mor"><mw><pos><c>det</c><s>art</s></pos><stem>la</stem><mk type="sfxf">f</mk><mk type="sfxf">sg</mk></mw></mor></w>
    <w>place<mor type="mor"><mw><pos><c>n</c></pos><stem>place</stem><mk type="sfxf">f</mk></mw></mor></w>
    <t type="p"><mor type="mor"><mt type="p"/></mor></t>

  </u>
  <u who="CHI" uID="u20">
    <w>y<mor type="mor"><mw><pos><c>pro</c><s>y</s></pos><stem>y</stem></mw></mor></w>
    <w>a<mor type="mor"><mw><pos><c>v</c><s>aux</s></pos><stem>avoir</stem><mk type="sfxf">PRES</mk><mk type="sfxf">3s</mk></mw></mor></w>
    <w>place<mor type="mor"><mw><pos><c>n</c></pos><stem>place</stem><mk type="sfxf">f</mk></mw></mor></w>
    <w>hein<mor type="mor"><mw><pos><c>co</c></pos><stem>hein</stem></mw></mor></w>
    <t type="q"><mor type="mor"><mt type="q"/></mor></t>

  </u>
  <u who="CHI" uID="u21">
    <w>pas<mor type="mor"><mw><pos><c>adv</c><s>neg</s></pos><stem>pas</stem></mw></mor></w>
    <w>de<mor type="mor"><mw><pos><c>prep</c></pos><stem>de</stem></mw></mor></w>
    <w>place<mor type="mor"><mw><pos><c>n</c></pos><stem>place</stem><mk type="sfxf">f</mk></mw></mor></w>
    <w>pour<mor type="mor"><mw><pos><c>prep</c></pos><stem>pour</stem></mw></mor></w>
    <w>se<mor type="mor"><mw><pos><c>pro</c><s>refl</s></pos><stem>se</stem></mw></mor></w>
    <w>garer<mor type="mor"><mw><pos><c>v</c></pos><stem>garer</stem><mk type="sfx">INF</mk></mw></mor></w>
    <t type="p"><mor type="mor"><mt type="p"/></mor></t>

  </u>
  <u who="CHI" uID="u22">
    <w>rien<mor type="mor"><mw><pos><c>adv</c><s>neg</s></pos><stem>rien</stem></mw></mor></w>
    <t type="p"><mor type="mor"><mt type="p"/></mor></t>

  </u>
  <u who="CHI" uID="u23">
    <w>là<mor type="mor"><mw><pos><c>adv</c><s>place</s></pos><stem>là</stem></mw></mor></w>
    <t type="p"><mor type="mor"><mt type="p"/></mor></t>

  </u>
  <u who="CHI" uID="u24">
    <w>i<shortening>l</shortening><mor type="mor"><mw><pos><c>pro</c><s>subj</s></pos><stem>il</stem></mw></mor></w>
    <w>monte<mor type="mor"><mw><pos><c>v</c></pos><stem>monter</stem><mk type="sfx">PRES</mk><mk type="sfxf">SUB</mk><mk type="sfxf">13s</mk></mw></mor></w>
    <w>sur<mor type="mor"><mw><pos><c>prep</c></pos><stem>sur</stem></mw></mor></w>
    <w>son<mor type="mor"><mw><pos><c>det</c><s>poss</s></pos><stem>son</stem><mk type="sfxf">m</mk><mk type="sfxf">sg</mk></mw></mor></w>
    <w>cheval<mor type="mor"><mw><pos><c>n</c></pos><stem>cheval</stem><mk type="sfxf">m</mk><mk type="sfxf">sg</mk></mw></mor></w>
    <t type="p"><mor type="mor"><mt type="p"/></mor></t>

  </u>
  <u who="CHI" uID="u25">
    <w>l'a<mor type="mor"><mw><pos><c>v</c><s>aux</s></pos><stem>avoir</stem><mk type="sfxf">PRES</mk><mk type="sfxf">3s</mk></mw><mor-pre><mw><pos><c>pro</c><s>subj</s></pos><stem>il</stem></mw></mor-pre></mor></w>
    <w>pas<mor type="mor"><mw><pos><c>adv</c><s>neg</s></pos><stem>pas</stem></mw></mor></w>
    <w>dormi<mor type="mor"><mw><pos><c>part</c></pos><stem>dormir</stem><mk type="sfx">PP</mk><mk type="sfxf">m</mk></mw></mor></w>
    <t type="p"><mor type="mor"><mt type="p"/></mor></t>

  </u>
  <u who="CHI" uID="u26">
    <w>regarde<mor type="mor"><mw><pos><c>v</c></pos><stem>regarder</stem><mk type="sfx">IMP</mk><mk type="sfxf">2s</mk></mw></mor></w>
    <w>y<mor type="mor"><mw><pos><c>pro</c><s>y</s></pos><stem>y</stem></mw></mor></w>
    <w>a<mor type="mor"><mw><pos><c>v</c><s>aux</s></pos><stem>avoir</stem><mk type="sfxf">PRES</mk><mk type="sfxf">3s</mk></mw></mor></w>
    <w>une<mor type="mor"><mw><pos><c>det</c><s>art</s></pos><stem>une</stem><mk type="sfxf">f</mk><mk type="sfxf">sg</mk></mw></mor></w>
    <w>place<mor type="mor"><mw><pos><c>n</c></pos><stem>place</stem><mk type="sfxf">f</mk></mw></mor></w>
    <t type="p"><mor type="mor"><mt type="p"/></mor></t>

  </u>
  <u who="CHI" uID="u27">
    <w>y<mor type="mor"><mw><pos><c>pro</c><s>y</s></pos><stem>y</stem></mw></mor></w>
    <w>a<mor type="mor"><mw><pos><c>v</c><s>aux</s></pos><stem>avoir</stem><mk type="sfxf">PRES</mk><mk type="sfxf">3s</mk></mw></mor></w>
    <w>une<mor type="mor"><mw><pos><c>det</c><s>art</s></pos><stem>une</stem><mk type="sfxf">f</mk><mk type="sfxf">sg</mk></mw></mor></w>
    <w>place<mor type="mor"><mw><pos><c>n</c></pos><stem>place</stem><mk type="sfxf">f</mk></mw></mor></w>
    <t type="p"><mor type="mor"><mt type="p"/></mor></t>

  </u>
  <u who="CHI" uID="u28">
    <w>pour<mor type="mor"><mw><pos><c>prep</c></pos><stem>pour</stem></mw></mor></w>
    <w>dormir<mor type="mor"><mw><pos><c>v</c></pos><stem>dormir</stem><mk type="sfx">INF</mk></mw></mor></w>
    <t type="p"><mor type="mor"><mt type="p"/></mor></t>

  </u>
  <u who="CHI" uID="u29">
    <w>l'a<mor type="mor"><mw><pos><c>v</c><s>aux</s></pos><stem>avoir</stem><mk type="sfxf">PRES</mk><mk type="sfxf">3s</mk></mw><mor-pre><mw><pos><c>pro</c><s>subj</s></pos><stem>il</stem></mw></mor-pre></mor></w>
    <w>dormi<mor type="mor"><mw><pos><c>part</c></pos><stem>dormir</stem><mk type="sfx">PP</mk><mk type="sfxf">m</mk></mw></mor></w>
    <t type="p"><mor type="mor"><mt type="p"/></mor></t>

  </u>
  <u who="CHI" uID="u30">
    <w>i<shortening>l</shortening><mor type="mor"><mw><pos><c>pro</c><s>subj</s></pos><stem>il</stem></mw></mor></w>
    <w>se<mor type="mor"><mw><pos><c>pro</c><s>refl</s></pos><stem>se</stem></mw></mor></w>
    <w>lève<mor type="mor"><mw><pos><c>v</c></pos><stem>lever</stem><mk type="sfx">PRES</mk><mk type="sfxf">SUB</mk><mk type="sfxf">13s</mk></mw></mor></w>
    <t type="p"><mor type="mor"><mt type="p"/></mor></t>

  </u>
  <u who="CHI" uID="u31">
    <w>l'a<mor type="mor"><mw><pos><c>v</c><s>aux</s></pos><stem>avoir</stem><mk type="sfxf">PRES</mk><mk type="sfxf">3s</mk></mw><mor-pre><mw><pos><c>pro</c><s>subj</s></pos><stem>il</stem></mw></mor-pre></mor></w>
    <w>dormi<mor type="mor"><mw><pos><c>part</c></pos><stem>dormir</stem><mk type="sfx">PP</mk><mk type="sfxf">m</mk></mw></mor></w>
    <t type="p"><mor type="mor"><mt type="p"/></mor></t>

  </u>
  <u who="CHI" uID="u32">
    <w>va<mor type="mor"><mw><pos><c>v</c><s>mdl</s></pos><stem>aller</stem><mk type="sfxf">PRES</mk><mk type="sfxf">3s</mk></mw></mor></w>
    <w>déjeuner<mor type="mor"><mw><mpfx>dé</mpfx><pos><c>v</c></pos><stem>jeuner</stem><mk type="sfx">INF</mk></mw></mor></w>
    <t type="p"><mor type="mor"><mt type="p"/></mor></t>

  </u>
  <u who="CHI" uID="u33">
    <w>i<shortening>l</shortening><mor type="mor"><mw><pos><c>pro</c><s>subj</s></pos><stem>il</stem></mw></mor></w>
    <w>va<mor type="mor"><mw><pos><c>v</c><s>mdl</s></pos><stem>aller</stem><mk type="sfxf">PRES</mk><mk type="sfxf">3s</mk></mw></mor></w>
    <w>manger<mor type="mor"><mw><pos><c>v</c></pos><stem>manger</stem><mk type="sfx">INF</mk></mw></mor></w>
    <w>des<mor type="mor"><mw><pos><c>prep</c></pos><stem>de</stem><mk type="sfxf">les</mk></mw></mor></w>
    <w>céréales<mor type="mor"><mw><pos><c>n</c></pos><stem>céréale</stem><mk type="sfxf">f</mk><mk type="sfx">PL</mk></mw></mor></w>
    <t type="p"><mor type="mor"><mt type="p"/></mor></t>

  </u>
  <u who="CHI" uID="u34">
    <w>des<mor type="mor"><mw><pos><c>prep</c></pos><stem>de</stem><mk type="sfxf">les</mk></mw></mor></w>
    <w>gâteaux<mor type="mor"><mw><pos><c>n</c></pos><stem>gâteau</stem><mk type="sfxf">m</mk><mk type="sfx">PL</mk></mw></mor></w>
    <t type="p"><mor type="mor"><mt type="p"/></mor></t>

  </u>
  <u who="CHI" uID="u35">
    <w>oui<mor type="mor"><mw><pos><c>co</c></pos><stem>oui</stem></mw><menx>yes</menx></mor></w>
    <t type="p"><mor type="mor"><mt type="p"/></mor></t>

  </u>
  <u who="CHI" uID="u36">
    <w>oui<mor type="mor"><mw><pos><c>co</c></pos><stem>oui</stem></mw><menx>yes</menx></mor></w>
    <t type="p"><mor type="mor"><mt type="p"/></mor></t>

  </u>
  <u who="CHI" uID="u37">
    <w>emmène<mor type="mor"><mw><pos><c>v</c></pos><stem>emmener</stem><mk type="sfx">PRES</mk><mk type="sfxf">SUB</mk><mk type="sfxf">13s</mk></mw></mor></w>
    <w>à<mor type="mor"><mw><pos><c>prep</c></pos><stem>à</stem></mw></mor></w>
    <w>l'école<mor type="mor"><mw><pos><c>n</c></pos><stem>école</stem><mk type="sfxf">f</mk></mw><mor-pre><mw><pos><c>det</c><s>art</s></pos><stem>le</stem></mw></mor-pre></mor></w>
    <t type="p"><mor type="mor"><mt type="p"/></mor></t>

  </u>
  <u who="CHI" uID="u38">
    <w>on<mor type="mor"><mw><pos><c>pro</c><s>subj</s></pos><stem>on</stem></mw></mor></w>
    <w>descend<mor type="mor"><mw><pos><c>v</c></pos><stem>descendre</stem><mk type="sfx">PRES</mk><mk type="sfxf">3s</mk></mw></mor></w>
    <w>là<mor type="mor"><mw><pos><c>adv</c><s>place</s></pos><stem>là</stem></mw></mor></w>
    <t type="p"><mor type="mor"><mt type="p"/></mor></t>

  </u>
  <u who="CHI" uID="u39">
    <w>comme-ça<mor type="mor"><mw><pos><c>adv</c></pos><stem>comme</stem><mk type="sfx">ça</mk></mw></mor></w>
    <t type="p"><mor type="mor"><mt type="p"/></mor></t>

  </u>
  <u who="CHI" uID="u40">
    <w>toboggan<mor type="mor"><mw><pos><c>n</c></pos><stem>toboggan</stem><mk type="sfxf">m</mk></mw></mor></w>
    <t type="p"><mor type="mor"><mt type="p"/></mor></t>

  </u>
  <u who="CHI" uID="u41">
    <w>un<mor type="mor"><mw><pos><c>det</c><s>art</s></pos><stem>un</stem><mk type="sfxf">m</mk><mk type="sfxf">sg</mk></mw></mor></w>
    <w>deux<mor type="mor"><mw><pos><c>n</c></pos><stem>deux</stem><mk type="sfxf">m</mk></mw></mor></w>
    <w>trois<mor type="mor"><mw><pos><c>n</c></pos><stem>trois</stem><mk type="sfxf">m</mk></mw></mor></w>
    <w>quatre<mor type="mor"><mw><pos><c>n</c></pos><stem>quatre</stem><mk type="sfxf">m</mk></mw></mor></w>
    <w>cinq<mor type="mor"><mw><pos><c>n</c></pos><stem>cinq</stem><mk type="sfxf">m</mk></mw></mor></w>
    <t type="p"><mor type="mor"><mt type="p"/></mor></t>

  </u>
  <u who="CHI" uID="u42">
    <w>il<mor type="mor"><mw><pos><c>pro</c><s>subj</s></pos><stem>il</stem></mw></mor></w>
    <w>est<mor type="mor"><mw><pos><c>v</c><s>aux</s></pos><stem>être</stem><mk type="sfxf">PRES</mk><mk type="sfxf">3s</mk></mw></mor></w>
    <w>tombé<mor type="mor"><mw><pos><c>part</c></pos><stem>tomber</stem><mk type="sfx">PP</mk><mk type="sfxf">m</mk></mw></mor></w>
    <t type="p"><mor type="mor"><mt type="p"/></mor></t>

  </u>
  <u who="CHI" uID="u43">
    <w>a<mor type="mor"><mw><pos><c>v</c><s>aux</s></pos><stem>avoir</stem><mk type="sfxf">PRES</mk><mk type="sfxf">3s</mk></mw></mor></w>
    <w>pas<mor type="mor"><mw><pos><c>adv</c><s>neg</s></pos><stem>pas</stem></mw></mor></w>
    <w>cassé<mor type="mor"><mw><pos><c>part</c></pos><stem>casser</stem><mk type="sfx">PP</mk><mk type="sfxf">m</mk></mw></mor></w>
    <w>mon<mor type="mor"><mw><pos><c>det</c><s>poss</s></pos><stem>mon</stem><mk type="sfxf">m</mk><mk type="sfxf">sg</mk></mw></mor></w>
    <w>nez<mor type="mor"><mw><pos><c>n</c></pos><stem>nez</stem><mk type="sfxf">m</mk></mw></mor></w>
    <t type="p"><mor type="mor"><mt type="p"/></mor></t>

  </u>
  <u who="CHI" uID="u44">
    <w>il<mor type="mor"><mw><pos><c>pro</c><s>subj</s></pos><stem>il</stem></mw></mor></w>
    <w>est<mor type="mor"><mw><pos><c>v</c><s>aux</s></pos><stem>être</stem><mk type="sfxf">PRES</mk><mk type="sfxf">3s</mk></mw></mor></w>
    <w>là<mor type="mor"><mw><pos><c>adv</c><s>place</s></pos><stem>là</stem></mw></mor></w>
    <w>mon<mor type="mor"><mw><pos><c>det</c><s>poss</s></pos><stem>mon</stem><mk type="sfxf">m</mk><mk type="sfxf">sg</mk></mw></mor></w>
    <w>nez<mor type="mor"><mw><pos><c>n</c></pos><stem>nez</stem><mk type="sfxf">m</mk></mw></mor></w>
    <t type="p"><mor type="mor"><mt type="p"/></mor></t>

  </u>
  <u who="CHI" uID="u45">
    <w>j'ai<mor type="mor"><mw><pos><c>v</c><s>aux</s></pos><stem>avoir</stem><mk type="sfxf">PRES</mk><mk type="sfxf">1s</mk></mw><mor-pre><mw><pos><c>pro</c><s>subj</s></pos><stem>je</stem></mw></mor-pre></mor></w>
    <w>pas<mor type="mor"><mw><pos><c>adv</c><s>neg</s></pos><stem>pas</stem></mw></mor></w>
    <w>cassé<mor type="mor"><mw><pos><c>part</c></pos><stem>casser</stem><mk type="sfx">PP</mk><mk type="sfxf">m</mk></mw></mor></w>
    <w>mon<mor type="mor"><mw><pos><c>det</c><s>poss</s></pos><stem>mon</stem><mk type="sfxf">m</mk><mk type="sfxf">sg</mk></mw></mor></w>
    <w>nez<mor type="mor"><mw><pos><c>n</c></pos><stem>nez</stem><mk type="sfxf">m</mk></mw></mor></w>
    <t type="p"><mor type="mor"><mt type="p"/></mor></t>

  </u>
  <u who="CHI" uID="u46">
    <w>j'ai<mor type="mor"><mw><pos><c>v</c><s>aux</s></pos><stem>avoir</stem><mk type="sfxf">PRES</mk><mk type="sfxf">1s</mk></mw><mor-pre><mw><pos><c>pro</c><s>subj</s></pos><stem>je</stem></mw></mor-pre></mor></w>
    <w>pas<mor type="mor"><mw><pos><c>adv</c><s>neg</s></pos><stem>pas</stem></mw></mor></w>
    <w>cassé<mor type="mor"><mw><pos><c>part</c></pos><stem>casser</stem><mk type="sfx">PP</mk><mk type="sfxf">m</mk></mw></mor></w>
    <w>mon<mor type="mor"><mw><pos><c>det</c><s>poss</s></pos><stem>mon</stem><mk type="sfxf">m</mk><mk type="sfxf">sg</mk></mw></mor></w>
    <w>bras<mor type="mor"><mw><pos><c>n</c></pos><stem>bras</stem><mk type="sfxf">m</mk></mw></mor></w>
    <t type="p"><mor type="mor"><mt type="p"/></mor></t>

  </u>
  <u who="CHI" uID="u47">
    <g><w>vroum<mor type="mor"><mw><pos><c>co</c></pos><stem>vroum</stem></mw><menx>car</menx></mor></w><r times="2"/></g>
    <t type="p"><mor type="mor"><mt type="p"/></mor></t>

  </u>
  <u who="CHI" uID="u48">
    <w>la<mor type="mor"><mw><pos><c>det</c><s>art</s></pos><stem>la</stem><mk type="sfxf">f</mk><mk type="sfxf">sg</mk></mw></mor></w>
    <w>voiture<mor type="mor"><mw><pos><c>n</c></pos><stem>voiture</stem><mk type="sfxf">f</mk></mw></mor></w>
    <w>cassée<mor type="mor"><mw><pos><c>part</c></pos><stem>casser</stem><mk type="sfx">PP</mk><mk type="sfxf">f</mk></mw></mor></w>
    <t type="p"><mor type="mor"><mt type="p"/></mor></t>

  </u>
  <u who="CHI" uID="u49">
    <w>oui<mor type="mor"><mw><pos><c>co</c></pos><stem>oui</stem></mw><menx>yes</menx></mor></w>
    <t type="p"><mor type="mor"><mt type="p"/></mor></t>

  </u>
  <u who="CHI" uID="u50">
    <w>là<mor type="mor"><mw><pos><c>adv</c><s>place</s></pos><stem>là</stem></mw></mor></w>
    <t type="p"><mor type="mor"><mt type="p"/></mor></t>

  </u>
  <u who="CHI" uID="u51">
    <w>c'est<mor type="mor"><mw><pos><c>v</c><s>aux</s></pos><stem>être</stem><mk type="sfxf">PRES</mk><mk type="sfxf">3s</mk></mw><mor-pre><mw><pos><c>pro</c><s>dem</s></pos><stem>ce</stem></mw></mor-pre></mor></w>
    <w>lui<mor type="mor"><mw><pos><c>pro</c><s>ind</s></pos><stem>lui</stem></mw></mor></w>
    <t type="p"><mor type="mor"><mt type="p"/></mor></t>

  </u>
  <u who="CHI" uID="u52">
    <w>l'a<mor type="mor"><mw><pos><c>v</c><s>aux</s></pos><stem>avoir</stem><mk type="sfxf">PRES</mk><mk type="sfxf">3s</mk></mw><mor-pre><mw><pos><c>pro</c><s>subj</s></pos><stem>il</stem></mw></mor-pre></mor></w>
    <w>pas<mor type="mor"><mw><pos><c>adv</c><s>neg</s></pos><stem>pas</stem></mw></mor></w>
    <w>bobo<mor type="mor"><mw><pos><c>n</c></pos><stem>bobo</stem><mk type="sfxf">m</mk></mw><menx>ouchie</menx></mor></w>
    <w>la<mor type="mor"><mw><pos><c>det</c><s>art</s></pos><stem>la</stem><mk type="sfxf">f</mk><mk type="sfxf">sg</mk></mw></mor></w>
    <w>voiture<mor type="mor"><mw><pos><c>n</c></pos><stem>voiture</stem><mk type="sfxf">f</mk></mw></mor></w>
    <t type="p"><mor type="mor"><mt type="p"/></mor></t>

  </u>
  <u who="CHI" uID="u53">
    <w>non<mor type="mor"><mw><pos><c>co</c></pos><stem>non</stem></mw><menx>no</menx></mor></w>
    <w>l'a<mor type="mor"><mw><pos><c>v</c><s>aux</s></pos><stem>avoir</stem><mk type="sfxf">PRES</mk><mk type="sfxf">3s</mk></mw><mor-pre><mw><pos><c>pro</c><s>subj</s></pos><stem>il</stem></mw></mor-pre></mor></w>
    <w>pas<mor type="mor"><mw><pos><c>adv</c><s>neg</s></pos><stem>pas</stem></mw></mor></w>
    <w>mal<mor type="mor"><mw><pos><c>adv</c></pos><stem>mal</stem></mw></mor></w>
    <w>la<mor type="mor"><mw><pos><c>det</c><s>art</s></pos><stem>la</stem><mk type="sfxf">f</mk><mk type="sfxf">sg</mk></mw></mor></w>
    <w>voiture<mor type="mor"><mw><pos><c>n</c></pos><stem>voiture</stem><mk type="sfxf">f</mk></mw></mor></w>
    <t type="p"><mor type="mor"><mt type="p"/></mor></t>

  </u>
  <u who="CHI" uID="u54">
    <w>ça<mor type="mor"><mw><pos><c>pro</c><s>dem</s></pos><stem>ça</stem></mw></mor></w>
    <t type="p"><mor type="mor"><mt type="p"/></mor></t>

  </u>
  <u who="CHI" uID="u55">
    <w>vroum<mor type="mor"><mw><pos><c>co</c></pos><stem>vroum</stem></mw><menx>car</menx></mor></w>
    <t type="e"><mor type="mor"><mt type="e"/></mor></t>

  </u>
  <u who="CHI" uID="u56">
    <w>ah<mor type="mor"><mw><pos><c>co</c></pos><stem>ah</stem></mw></mor></w>
    <w>va<mor type="mor"><mw><pos><c>v</c><s>mdl</s></pos><stem>aller</stem><mk type="sfxf">PRES</mk><mk type="sfxf">3s</mk></mw></mor></w>
    <w>tomber<mor type="mor"><mw><pos><c>v</c></pos><stem>tomber</stem><mk type="sfx">INF</mk></mw></mor></w>
    <w>fille<mor type="mor"><mw><pos><c>n</c></pos><stem>fille</stem><mk type="sfxf">f</mk></mw></mor></w>
    <t type="p"><mor type="mor"><mt type="p"/></mor></t>

  </u>
  <u who="CHI" uID="u57">
    <w>est<mor type="mor"><mw><pos><c>v</c><s>aux</s></pos><stem>être</stem><mk type="sfxf">PRES</mk><mk type="sfxf">3s</mk></mw></mor></w>
    <w>tombé<mor type="mor"><mw><pos><c>part</c></pos><stem>tomber</stem><mk type="sfx">PP</mk><mk type="sfxf">m</mk></mw></mor></w>
    <t type="p"><mor type="mor"><mt type="p"/></mor></t>

  </u>
  <u who="CHI" uID="u58">
    <w>c'est<mor type="mor"><mw><pos><c>v</c><s>aux</s></pos><stem>être</stem><mk type="sfxf">PRES</mk><mk type="sfxf">3s</mk></mw><mor-pre><mw><pos><c>pro</c><s>dem</s></pos><stem>ce</stem></mw></mor-pre></mor></w>
    <w>même<mor type="mor"><mw><pos><c>adv</c></pos><stem>même</stem></mw></mor></w>
    <t type="p"><mor type="mor"><mt type="p"/></mor></t>

  </u>
  <u who="CHI" uID="u59">
    <w>si<mor type="mor"><mw><pos><c>adv</c></pos><stem>si</stem></mw></mor></w>
    <w>c'est<mor type="mor"><mw><pos><c>v</c><s>aux</s></pos><stem>être</stem><mk type="sfxf">PRES</mk><mk type="sfxf">3s</mk></mw><mor-pre><mw><pos><c>pro</c><s>dem</s></pos><stem>ce</stem></mw></mor-pre></mor></w>
    <w>même<mor type="mor"><mw><pos><c>adv</c></pos><stem>même</stem></mw></mor></w>
    <t type="p"><mor type="mor"><mt type="p"/></mor></t>

  </u>
  <u who="CHI" uID="u60">
    <w>ça<mor type="mor"><mw><pos><c>pro</c><s>dem</s></pos><stem>ça</stem></mw></mor></w>
    <w>c'est<mor type="mor"><mw><pos><c>v</c><s>aux</s></pos><stem>être</stem><mk type="sfxf">PRES</mk><mk type="sfxf">3s</mk></mw><mor-pre><mw><pos><c>pro</c><s>dem</s></pos><stem>ce</stem></mw></mor-pre></mor></w>
    <w>orange<mor type="mor"><mw><pos><c>n</c></pos><stem>orange</stem></mw></mor></w>
    <t type="p"><mor type="mor"><mt type="p"/></mor></t>

  </u>
  <u who="CHI" uID="u61">
    <w>ça<mor type="mor"><mw><pos><c>pro</c><s>dem</s></pos><stem>ça</stem></mw></mor></w>
    <w>c'est<mor type="mor"><mw><pos><c>v</c><s>aux</s></pos><stem>être</stem><mk type="sfxf">PRES</mk><mk type="sfxf">3s</mk></mw><mor-pre><mw><pos><c>pro</c><s>dem</s></pos><stem>ce</stem></mw></mor-pre></mor></w>
    <w>vert<mor type="mor"><mw><pos><c>adj</c></pos><stem>vert</stem><mk type="sfxf">m</mk></mw></mor></w>
    <t type="p"><mor type="mor"><mt type="p"/></mor></t>

  </u>
  <u who="CHI" uID="u62">
    <w>il<mor type="mor"><mw><pos><c>pro</c><s>subj</s></pos><stem>il</stem></mw></mor></w>
    <w>est<mor type="mor"><mw><pos><c>v</c><s>aux</s></pos><stem>être</stem><mk type="sfxf">PRES</mk><mk type="sfxf">3s</mk></mw></mor></w>
    <w>sale<mor type="mor"><mw><pos><c>adj</c></pos><stem>sale</stem></mw></mor></w>
    <t type="p"><mor type="mor"><mt type="p"/></mor></t>

  </u>
  <u who="CHI" uID="u63">
    <w>la<mor type="mor"><mw><pos><c>det</c><s>art</s></pos><stem>la</stem><mk type="sfxf">f</mk><mk type="sfxf">sg</mk></mw></mor></w>
    <w>tête<mor type="mor"><mw><pos><c>n</c></pos><stem>tête</stem><mk type="sfxf">f</mk></mw></mor></w>
    <w>sale<mor type="mor"><mw><pos><c>adj</c></pos><stem>sale</stem></mw></mor></w>
    <t type="p"><mor type="mor"><mt type="p"/></mor></t>

  </u>
  <u who="CHI" uID="u64">
    <w>il<mor type="mor"><mw><pos><c>pro</c><s>subj</s></pos><stem>il</stem></mw></mor></w>
    <w>a<mor type="mor"><mw><pos><c>v</c><s>aux</s></pos><stem>avoir</stem><mk type="sfxf">PRES</mk><mk type="sfxf">3s</mk></mw></mor></w>
    <w>pas<mor type="mor"><mw><pos><c>adv</c><s>neg</s></pos><stem>pas</stem></mw></mor></w>
    <w>lavé<mor type="mor"><mw><pos><c>part</c></pos><stem>laver</stem><mk type="sfx">PP</mk><mk type="sfxf">m</mk></mw></mor></w>
    <w>le<mor type="mor"><mw><pos><c>det</c><s>art</s></pos><stem>le</stem><mk type="sfxf">m</mk><mk type="sfxf">sg</mk></mw></mor></w>
    <w>bout<mor type="mor"><mw><pos><c>n</c></pos><stem>bout</stem><mk type="sfxf">m</mk></mw></mor></w>
    <w>de<mor type="mor"><mw><pos><c>prep</c></pos><stem>de</stem></mw></mor></w>
    <w>son<mor type="mor"><mw><pos><c>det</c><s>poss</s></pos><stem>son</stem><mk type="sfxf">m</mk><mk type="sfxf">sg</mk></mw></mor></w>
    <w>nez<mor type="mor"><mw><pos><c>n</c></pos><stem>nez</stem><mk type="sfxf">m</mk></mw></mor></w>
    <t type="p"><mor type="mor"><mt type="p"/></mor></t>

  </u>
  <u who="CHI" uID="u65">
    <w>oh<mor type="mor"><mw><pos><c>co</c></pos><stem>oh</stem></mw></mor></w>
    <w>il<mor type="mor"><mw><pos><c>pro</c><s>subj</s></pos><stem>il</stem></mw></mor></w>
    <w>a<mor type="mor"><mw><pos><c>v</c><s>aux</s></pos><stem>avoir</stem><mk type="sfxf">PRES</mk><mk type="sfxf">3s</mk></mw></mor></w>
    <w>fait<mor type="mor"><mw><pos><c>part</c></pos><stem>faire</stem><mk type="sfx">PP</mk><mk type="sfxf">m</mk></mw></mor></w>
    <w>caca<mor type="mor"><mw><pos><c>n</c></pos><stem>caca</stem><mk type="sfxf">m</mk></mw><menx>poopoo</menx></mor></w>
    <t type="p"><mor type="mor"><mt type="p"/></mor></t>

  </u>
  <u who="CHI" uID="u66">
    <w>ça_y_est<mor type="mor"><mw><pos><c>co</c></pos><stem>ça_y_est</stem></mw></mor></w>
    <t type="e"><mor type="mor"><mt type="e"/></mor></t>

  </u>
  <u who="CHI" uID="u67">
    <w>elle<mor type="mor"><mw><pos><c>pro</c><s>subj</s></pos><stem>elle</stem></mw></mor></w>
    <w>a<mor type="mor"><mw><pos><c>v</c><s>aux</s></pos><stem>avoir</stem><mk type="sfxf">PRES</mk><mk type="sfxf">3s</mk></mw></mor></w>
    <w>envie<mor type="mor"><mw><pos><c>n</c></pos><stem>envie</stem><mk type="sfxf">f</mk></mw></mor></w>
    <w>de<mor type="mor"><mw><pos><c>prep</c></pos><stem>de</stem></mw></mor></w>
    <w>faire<mor type="mor"><mw><pos><c>v</c><s>mdl</s></pos><stem>faire</stem><mk type="sfx">INF</mk></mw></mor></w>
    <w>caca<mor type="mor"><mw><pos><c>n</c></pos><stem>caca</stem><mk type="sfxf">m</mk></mw><menx>poopoo</menx></mor></w>
    <t type="p"><mor type="mor"><mt type="p"/></mor></t>

  </u>
  <u who="CHI" uID="u68">
    <w>regarde<mor type="mor"><mw><pos><c>v</c></pos><stem>regarder</stem><mk type="sfx">PRES</mk><mk type="sfxf">SUB</mk><mk type="sfxf">13s</mk></mw></mor></w>
    <w>l'est<mor type="mor"><mw><pos><c>v</c><s>aux</s></pos><stem>être</stem><mk type="sfxf">PRES</mk><mk type="sfxf">3s</mk></mw><mor-pre><mw><pos><c>pro</c><s>subj</s></pos><stem>il</stem></mw></mor-pre></mor></w>
    <w>sale<mor type="mor"><mw><pos><c>adj</c></pos><stem>sale</stem></mw></mor></w>
    <t type="p"><mor type="mor"><mt type="p"/></mor></t>

  </u>
  <u who="CHI" uID="u69">
    <w>caca<mor type="mor"><mw><pos><c>n</c></pos><stem>caca</stem><mk type="sfxf">m</mk></mw><menx>poopoo</menx></mor></w>
    <w>partout<mor type="mor"><mw><pos><c>adv</c></pos><stem>partout</stem></mw></mor></w>
    <t type="p"><mor type="mor"><mt type="p"/></mor></t>

  </u>
  <u who="CHI" uID="u70">
    <w>oh<mor type="mor"><mw><pos><c>co</c></pos><stem>oh</stem></mw></mor></w>
    <w>l'est<mor type="mor"><mw><pos><c>v</c><s>aux</s></pos><stem>être</stem><mk type="sfxf">PRES</mk><mk type="sfxf">3s</mk></mw><mor-pre><mw><pos><c>pro</c><s>subj</s></pos><stem>il</stem></mw></mor-pre></mor></w>
    <w>tombé<mor type="mor"><mw><pos><c>part</c></pos><stem>tomber</stem><mk type="sfx">PP</mk><mk type="sfxf">m</mk></mw></mor></w>
    <t type="p"><mor type="mor"><mt type="p"/></mor></t>

  </u>
  <u who="CHI" uID="u71">
    <w>vois<mor type="mor"><mw><pos><c>v</c></pos><stem>voir</stem><mk type="sfxf">IMP</mk><mk type="sfxf">PRES</mk><mk type="sfxf">12s</mk></mw></mor></w>
    <w>pas<mor type="mor"><mw><pos><c>adv</c><s>neg</s></pos><stem>pas</stem></mw></mor></w>
    <t type="p"><mor type="mor"><mt type="p"/></mor></t>

  </u>
  <u who="CHI" uID="u72">
    <w>sur<mor type="mor"><mw><pos><c>prep</c></pos><stem>sur</stem></mw></mor></w>
    <w>la<mor type="mor"><mw><pos><c>det</c><s>art</s></pos><stem>la</stem><mk type="sfxf">f</mk><mk type="sfxf">sg</mk></mw></mor></w>
    <w>table<mor type="mor"><mw><pos><c>n</c></pos><stem>table</stem><mk type="sfxf">f</mk></mw></mor></w>
    <t type="p"><mor type="mor"><mt type="p"/></mor></t>

  </u>
  <u who="CHI" uID="u73">
    <w>l'est<mor type="mor"><mw><pos><c>v</c><s>aux</s></pos><stem>être</stem><mk type="sfxf">PRES</mk><mk type="sfxf">3s</mk></mw><mor-pre><mw><pos><c>pro</c><s>subj</s></pos><stem>il</stem></mw></mor-pre></mor></w>
    <w>pas<mor type="mor"><mw><pos><c>adv</c><s>neg</s></pos><stem>pas</stem></mw></mor></w>
    <w>là<mor type="mor"><mw><pos><c>adv</c><s>place</s></pos><stem>là</stem></mw></mor></w>
    <t type="p"><mor type="mor"><mt type="p"/></mor></t>

  </u>
  <u who="CHI" uID="u74">
    <w>ah<mor type="mor"><mw><pos><c>co</c></pos><stem>ah</stem></mw></mor></w>
    <t type="e"><mor type="mor"><mt type="e"/></mor></t>

  </u>
  <u who="CHI" uID="u75">
    <w>chaise<mor type="mor"><mw><pos><c>n</c></pos><stem>chaise</stem><mk type="sfxf">f</mk></mw></mor></w>
    <t type="p"><mor type="mor"><mt type="p"/></mor></t>

  </u>
  <u who="CHI" uID="u76">
    <w>regarde<mor type="mor"><mw><pos><c>v</c></pos><stem>regarder</stem><mk type="sfx">IMP</mk><mk type="sfxf">2s</mk></mw></mor></w>
    <w>là<mor type="mor"><mw><pos><c>adv</c><s>place</s></pos><stem>là</stem></mw></mor></w>
    <t type="p"><mor type="mor"><mt type="p"/></mor></t>

  </u>
  <u who="CHI" uID="u77">
    <w>il<mor type="mor"><mw><pos><c>pro</c><s>subj</s></pos><stem>il</stem></mw></mor></w>
    <w>regarde<mor type="mor"><mw><pos><c>v</c></pos><stem>regarder</stem><mk type="sfx">PRES</mk><mk type="sfxf">SUB</mk><mk type="sfxf">13s</mk></mw></mor></w>
    <w>la<mor type="mor"><mw><pos><c>det</c><s>art</s></pos><stem>la</stem><mk type="sfxf">f</mk><mk type="sfxf">sg</mk></mw></mor></w>
    <w>télé<mor type="mor"><mw><pos><c>n</c></pos><stem>télé</stem><mk type="sfxf">f</mk></mw><menx>television</menx></mor></w>
    <t type="p"><mor type="mor"><mt type="p"/></mor></t>

  </u>
  <u who="CHI" uID="u78">
    <w>t'as<mor type="mor"><mw><pos><c>v</c><s>aux</s></pos><stem>avoir</stem><mk type="sfxf">PRES</mk><mk type="sfxf">2s</mk></mw><mor-pre><mw><pos><c>pro</c><s>subj</s></pos><stem>tu</stem></mw></mor-pre></mor></w>
    <w>vu<mor type="mor"><mw><pos><c>part</c></pos><stem>voir</stem><mk type="sfxf">PP</mk><mk type="sfxf">m</mk></mw></mor></w>
    <t type="p"><mor type="mor"><mt type="p"/></mor></t>

  </u>
  <u who="CHI" uID="u79">
    <w>regarde<mor type="mor"><mw><pos><c>v</c></pos><stem>regarder</stem><mk type="sfx">IMP</mk><mk type="sfxf">2s</mk></mw></mor></w>
    <w>télé<mor type="mor"><mw><pos><c>n</c></pos><stem>télé</stem><mk type="sfxf">f</mk></mw><menx>television</menx></mor></w>
    <w>là<mor type="mor"><mw><pos><c>adv</c><s>place</s></pos><stem>là</stem></mw></mor></w>
    <w>c'est<mor type="mor"><mw><pos><c>v</c><s>exist</s></pos><stem>être</stem><mk type="sfxf">PRES</mk><mk type="sfxf">3s</mk></mw><mor-pre><mw><pos><c>pro</c><s>dem</s></pos><stem>ce</stem></mw></mor-pre></mor></w>
    <w>fini<mor type="mor"><mw><pos><c>part</c></pos><stem>finir</stem><mk type="sfx">PP</mk><mk type="sfxf">m</mk></mw></mor></w>
    <t type="p"><mor type="mor"><mt type="p"/></mor></t>

  </u>
  <u who="CHI" uID="u80">
    <w>ah<mor type="mor"><mw><pos><c>co</c></pos><stem>ah</stem></mw></mor></w>
    <w>non<mor type="mor"><mw><pos><c>co</c></pos><stem>non</stem></mw><menx>no</menx></mor></w>
    <t type="e"><mor type="mor"><mt type="e"/></mor></t>

  </u>
  <u who="CHI" uID="u81">
    <w>elle<mor type="mor"><mw><pos><c>pro</c><s>subj</s></pos><stem>elle</stem></mw></mor></w>
    <w>est<mor type="mor"><mw><pos><c>v</c><s>aux</s></pos><stem>être</stem><mk type="sfxf">PRES</mk><mk type="sfxf">3s</mk></mw></mor></w>
    <w>là<mor type="mor"><mw><pos><c>adv</c><s>place</s></pos><stem>là</stem></mw></mor></w>
    <w>son<mor type="mor"><mw><pos><c>det</c><s>poss</s></pos><stem>son</stem><mk type="sfxf">m</mk><mk type="sfxf">sg</mk></mw></mor></w>
    <w>lit<mor type="mor"><mw><pos><c>n</c></pos><stem>lit</stem><mk type="sfxf">m</mk></mw></mor></w>
    <t type="p"><mor type="mor"><mt type="p"/></mor></t>

  </u>
  <u who="CHI" uID="u82">
    <w>bon<mor type="mor"><mw><pos><c>co</c></pos><stem>bon</stem></mw></mor></w>
    <w>i<shortening>l</shortening><mor type="mor"><mw><pos><c>pro</c><s>subj</s></pos><stem>il</stem></mw></mor></w>
    <w>fait<mor type="mor"><mw><pos><c>v</c><s>mdllex</s></pos><stem>faire</stem><mk type="sfx">PRES</mk><mk type="sfxf">3s</mk></mw></mor></w>
    <w>dodo<mor type="mor"><mw><pos><c>co</c></pos><stem>dodo</stem></mw></mor></w>
    <t type="p"><mor type="mor"><mt type="p"/></mor></t>

  </u>
  <u who="CHI" uID="u83">
    <w>y<mor type="mor"><mw><pos><c>pro</c><s>y</s></pos><stem>y</stem></mw></mor></w>
    <w>a<mor type="mor"><mw><pos><c>v</c><s>aux</s></pos><stem>avoir</stem><mk type="sfxf">PRES</mk><mk type="sfxf">3s</mk></mw></mor></w>
    <w>beaucoup<mor type="mor"><mw><pos><c>adv</c></pos><stem>beaucoup</stem></mw></mor></w>
    <w>de<mor type="mor"><mw><pos><c>prep</c></pos><stem>de</stem></mw></mor></w>
    <w>place<mor type="mor"><mw><pos><c>n</c></pos><stem>place</stem><mk type="sfxf">f</mk></mw></mor></w>
    <t type="p"><mor type="mor"><mt type="p"/></mor></t>

  </u>
  <u who="CHI" uID="u84">
    <w>ça<mor type="mor"><mw><pos><c>pro</c><s>dem</s></pos><stem>ça</stem></mw></mor></w>
    <w>c'est<mor type="mor"><mw><pos><c>v</c><s>aux</s></pos><stem>être</stem><mk type="sfxf">PRES</mk><mk type="sfxf">3s</mk></mw><mor-pre><mw><pos><c>pro</c><s>dem</s></pos><stem>ce</stem></mw></mor-pre></mor></w>
    <w>un<mor type="mor"><mw><pos><c>det</c><s>art</s></pos><stem>un</stem><mk type="sfxf">m</mk><mk type="sfxf">sg</mk></mw></mor></w>
    <w>grand<mor type="mor"><mw><pos><c>adj</c></pos><stem>grand</stem><mk type="sfxf">m</mk></mw></mor></w>
    <w>lit<mor type="mor"><mw><pos><c>n</c></pos><stem>lit</stem><mk type="sfxf">m</mk></mw></mor></w>
    <t type="p"><mor type="mor"><mt type="p"/></mor></t>

  </u>
  <u who="CHI" uID="u85">
    <w>y<mor type="mor"><mw><pos><c>pro</c><s>y</s></pos><stem>y</stem></mw></mor></w>
    <w>a<mor type="mor"><mw><pos><c>v</c><s>aux</s></pos><stem>avoir</stem><mk type="sfxf">PRES</mk><mk type="sfxf">3s</mk></mw></mor></w>
    <w>une<mor type="mor"><mw><pos><c>det</c><s>art</s></pos><stem>une</stem><mk type="sfxf">f</mk><mk type="sfxf">sg</mk></mw></mor></w>
    <w>place<mor type="mor"><mw><pos><c>n</c></pos><stem>place</stem><mk type="sfxf">f</mk></mw></mor></w>
    <t type="p"><mor type="mor"><mt type="p"/></mor></t>

  </u>
  <u who="CHI" uID="u86">
    <w>i<shortening>l</shortening><mor type="mor"><mw><pos><c>pro</c><s>subj</s></pos><stem>il</stem></mw></mor></w>
    <w>fait<mor type="mor"><mw><pos><c>v</c><s>mdllex</s></pos><stem>faire</stem><mk type="sfx">PRES</mk><mk type="sfxf">3s</mk></mw></mor></w>
    <w>dodo<mor type="mor"><mw><pos><c>co</c></pos><stem>dodo</stem></mw></mor></w>
    <t type="p"><mor type="mor"><mt type="p"/></mor></t>

  </u>
  <u who="CHI" uID="u87">
    <w>oh_non<mor type="mor"><mw><pos><c>co</c></pos><stem>oh_non</stem></mw></mor></w>
    <w>l'est<mor type="mor"><mw><pos><c>v</c><s>aux</s></pos><stem>être</stem><mk type="sfxf">PRES</mk><mk type="sfxf">3s</mk></mw><mor-pre><mw><pos><c>pro</c><s>subj</s></pos><stem>il</stem></mw></mor-pre></mor></w>
    <w>pas<mor type="mor"><mw><pos><c>adv</c><s>neg</s></pos><stem>pas</stem></mw></mor></w>
    <w>tombé<mor type="mor"><mw><pos><c>part</c></pos><stem>tomber</stem><mk type="sfx">PP</mk><mk type="sfxf">m</mk></mw></mor></w>
    <t type="p"><mor type="mor"><mt type="p"/></mor></t>

  </u>
  <u who="CHI" uID="u88">
    <w>ah<mor type="mor"><mw><pos><c>co</c></pos><stem>ah</stem></mw></mor></w>
    <w>non<mor type="mor"><mw><pos><c>co</c></pos><stem>non</stem></mw><menx>no</menx></mor></w>
    <w>l'est<mor type="mor"><mw><pos><c>v</c><s>aux</s></pos><stem>être</stem><mk type="sfxf">PRES</mk><mk type="sfxf">3s</mk></mw><mor-pre><mw><pos><c>pro</c><s>subj</s></pos><stem>il</stem></mw></mor-pre></mor></w>
    <w>pas<mor type="mor"><mw><pos><c>adv</c><s>neg</s></pos><stem>pas</stem></mw></mor></w>
    <w>tombé<mor type="mor"><mw><pos><c>part</c></pos><stem>tomber</stem><mk type="sfx">PP</mk><mk type="sfxf">m</mk></mw></mor></w>
    <t type="p"><mor type="mor"><mt type="p"/></mor></t>

  </u>
  <u who="CHI" uID="u89">
    <w>regarde<mor type="mor"><mw><pos><c>v</c></pos><stem>regarder</stem><mk type="sfx">IMP</mk><mk type="sfxf">2s</mk></mw></mor></w>
    <w>i<shortening>l</shortening><mor type="mor"><mw><pos><c>pro</c><s>subj</s></pos><stem>il</stem></mw></mor></w>
    <w>roule<mor type="mor"><mw><pos><c>v</c></pos><stem>rouler</stem><mk type="sfx">PRES</mk><mk type="sfxf">SUB</mk><mk type="sfxf">13s</mk></mw></mor></w>
    <t type="p"><mor type="mor"><mt type="p"/></mor></t>

  </u>
  <u who="CHI" uID="u90">
    <w>ça<mor type="mor"><mw><pos><c>pro</c><s>dem</s></pos><stem>ça</stem></mw></mor></w>
    <w>roule<mor type="mor"><mw><pos><c>v</c></pos><stem>rouler</stem><mk type="sfx">PRES</mk><mk type="sfxf">SUB</mk><mk type="sfxf">13s</mk></mw></mor></w>
    <t type="p"><mor type="mor"><mt type="p"/></mor></t>

  </u>
</CHAT>